{"media_type":1,"has_dash_audio":false,"is_completed":true,"total_bytes":404752075,"downloaded_bytes":404752075,"title":"某科学的超电磁炮","type_tag":"lua.flv.bb2api.80","cover":"http:\/\/i0.hdslb.com\/bfs\/bangumi\/bf7fc439d82e7d8ccfa827236963c72b94c6b7ed.jpg","prefered_video_quality":80,"guessed_total_bytes":0,"total_time_milli":1510419,"danmaku_count":3000,"time_update_stamp":1608740638219,"time_create_stamp":1608740581658,"season_id":"425","source":{"av_id":3934631,"cid":48126815,"website":"bangumi"},"ep":{"av_id":3934631,"page":0,"danmaku":48126815,"cover":"http:\/\/i0.hdslb.com\/bfs\/bangumi\/bf7fc439d82e7d8ccfa827236963c72b94c6b7ed.jpg","episode_id":84340,"index":"1","index_title":"电击使 Electro Master","from":"bangumi","season_type":1,"width":0,"height":0,"rotate":0}}