{"media_type":1,"has_dash_audio":false,"is_completed":true,"total_bytes":264655691,"downloaded_bytes":264655691,"title":"工作细胞 第二季","type_tag":"lua.flv.bb2api.80","cover":"http:\/\/i0.hdslb.com\/bfs\/bangumi\/3e606917728ec24602d27ee8d03f6e779d2779ea.jpg","video_quality":80,"prefered_video_quality":80,"guessed_total_bytes":0,"total_time_milli":1405115,"danmaku_count":3000,"time_update_stamp":1614495247513,"time_create_stamp":1614482575380,"can_play_in_advance":true,"interrupt_transform_temp_file":false,"quality_pithy_description":"","quality_superscript":"","cache_version_code":6160500,"preferred_audio_quality":0,"audio_quality":0,"season_id":"36174","source":{"av_id":671946236,"cid":303641131,"website":"bangumi","webvideo_id":""},"ep":{"av_id":671946236,"page":7,"danmaku":303641131,"cover":"http:\/\/i0.hdslb.com\/bfs\/archive\/1c61a2545684b94c8bb1cfd7a0ad50ca2126b685.jpg","episode_id":373885,"index":"8","index_title":"癌细胞Ⅱ（后篇）","from":"bangumi","season_type":1,"width":1920,"height":1080,"rotate":0,"link":"https:\/\/www.bilibili.com\/bangumi\/play\/ep373885","bvid":"BV1AU4y1p76B"}}